bossconf/__init__.py
bossconf/bossconf.py
bossconf/package_data.dat
bossconf/token_injector.py
bossconf-0.1a16.dist-info/DESCRIPTION.rst
bossconf-0.1a16.dist-info/METADATA
bossconf-0.1a16.dist-info/RECORD
bossconf-0.1a16.dist-info/WHEEL
bossconf-0.1a16.dist-info/entry_points.txt
bossconf-0.1a16.dist-info/metadata.json
bossconf-0.1a16.dist-info/top_level.txt
